datatoword/__init__.py
datatoword/conftest.py
datatoword/datatoword.py
datatoword/loaders/__init__.py
datatoword/loaders/csv.py
datatoword/loaders/factory.py
datatoword/loaders/json.py
datatoword/loaders/tests.py
datatoword/tests.py
datatoword-0.7.0.dist-info/LICENSE
datatoword-0.7.0.dist-info/METADATA
datatoword-0.7.0.dist-info/WHEEL
datatoword-0.7.0.dist-info/RECORD
