Metadata-Version: 2.1
Name: datatoword
Version: 0.7.0
Summary: 一個將資料轉換為文本的小工具，可提升 RAG 查詢的效率。
Home-page: https://github.com/nickchen1998/DataToWord
License: Apache-2.0
Author: nick
Author-email: nickchen1998@gmail.com
Requires-Python: >=3.11,<4.0
Classifier: License :: OSI Approved :: Apache Software License
Classifier: Programming Language :: Python :: 3
Classifier: Programming Language :: Python :: 3.11
Classifier: Programming Language :: Python :: 3.12
Requires-Dist: langchain (>=0.2.14,<0.3.0)
Requires-Dist: langchain-community (>=0.2.12,<0.3.0)
Requires-Dist: langchain-openai (>=0.1.22,<0.2.0)
Requires-Dist: python-dotenv (>=1.0.1,<2.0.0)
